deepgnn/__init__.py
deepgnn/arg_types.py
deepgnn/log_consts.py
deepgnn/logging_utils.py
deepgnn/train_types.py
deepgnn/tf/__init__.py
deepgnn/tf/common/__init__.py
deepgnn/tf/common/args.py
deepgnn/tf/common/base_trainer.py
deepgnn/tf/common/dataset.py
deepgnn/tf/common/dist_sync.py
deepgnn/tf/common/hooks.py
deepgnn/tf/common/horovod_trainer.py
deepgnn/tf/common/ps_trainer.py
deepgnn/tf/common/test_helper.py
deepgnn/tf/common/test_trainer.py
deepgnn/tf/common/test_trainer_tf2.py
deepgnn/tf/common/tf2_horovod_trainer.py
deepgnn/tf/common/tf2_trainer.py
deepgnn/tf/common/trainer.py
deepgnn/tf/common/trainer_factory.py
deepgnn/tf/common/utils.py
deepgnn/tf/encoders/__init__.py
deepgnn/tf/encoders/att_encoder.py
deepgnn/tf/encoders/han_encoder.py
deepgnn/tf/layers/__init__.py
deepgnn/tf/layers/attention_header.py
deepgnn/tf/layers/base.py
deepgnn/tf/nn/__init__.py
deepgnn/tf/nn/gat_conv.py
deepgnn/tf/nn/gcn_conv.py
deepgnn/tf/nn/metrics.py
deepgnn/tf/nn/sage_conv.py
deepgnn/tf/nn/test_conv.py
deepgnn_tf-0.1.60.dist-info/METADATA
deepgnn_tf-0.1.60.dist-info/WHEEL
deepgnn_tf-0.1.60.dist-info/top_level.txt
deepgnn_tf-0.1.60.dist-info/RECORD
